qgpu/__init__.py
qgpu-0.0.1.dist-info/METADATA
qgpu-0.0.1.dist-info/WHEEL
qgpu-0.0.1.dist-info/top_level.txt
qgpu-0.0.1.dist-info/RECORD
