Metadata-Version: 2.1
Name: qgpu
Version: 0.0.1
Summary: 2D QG on GPU
Home-page: https://www.python.org/
Author: thl
Author-email: happysky111999@gmail.com
License: UNKNOWN
Platform: UNKNOWN
